Metadata-Version: 2.1
Name: tinyprompt
Version: 0.1.0
Summary: Tiny Handy Prompting Lib
Home-page: https://github.com/sirosen/tinyprompt
Author: Stephen Rosen
Author-email: sirosen@globus.org
License: UNKNOWN
Keywords: cli,prompt,utility
Platform: UNKNOWN
Classifier: Development Status :: 3 - Alpha
Classifier: Intended Audience :: Developers
Classifier: License :: OSI Approved :: Apache Software License
Classifier: Operating System :: MacOS :: MacOS X
Classifier: Operating System :: Microsoft :: Windows
Classifier: Operating System :: POSIX
Classifier: Programming Language :: Python
Classifier: Programming Language :: Python :: 3.5
Classifier: Programming Language :: Python :: 3.6
Classifier: Programming Language :: Python :: 3.7
Provides-Extra: development
